atomicshop/__init__.py
atomicshop/_create_pdf_demo.py
atomicshop/_patch_import.py
atomicshop/appointment_management.py
atomicshop/certificates.py
atomicshop/command_line_processing.py
atomicshop/config_init.py
atomicshop/console_output.py
atomicshop/console_user_response.py
atomicshop/consoles.py
atomicshop/datetimes.py
atomicshop/diff_check.py
atomicshop/dns.py
atomicshop/domains.py
atomicshop/emails.py
atomicshop/filesystem.py
atomicshop/functions.py
atomicshop/get_process_list.py
atomicshop/get_process_name_cmd_dll.py
atomicshop/hashing.py
atomicshop/http_parse.py
atomicshop/inspect_wrapper.py
atomicshop/ip_addresses.py
atomicshop/keyboard_press.py
atomicshop/networks.py
atomicshop/on_exit.py
atomicshop/package_mains_processor.py
atomicshop/print_api.py
atomicshop/process.py
atomicshop/python_file_patcher.py
atomicshop/python_functions.py
atomicshop/question_answer_engine.py
atomicshop/queues.py
atomicshop/scheduling.py
atomicshop/sound.py
atomicshop/speech_recognize.py
atomicshop/ssh_remote.py
atomicshop/sys_functions.py
atomicshop/system_resource_monitor.py
atomicshop/system_resources.py
atomicshop/tempfiles.py
atomicshop/timer.py
atomicshop/urls.py
atomicshop/uuids.py
atomicshop/venvs.py
atomicshop/versioning.py
atomicshop/virtualization.py
atomicshop/web.py
atomicshop/websocket_parse.py
atomicshop/a_mains/dns_gateway_setting.py
atomicshop/a_mains/get_local_tcp_ports.py
atomicshop/a_mains/github_wrapper.py
atomicshop/a_mains/install_ca_certificate.py
atomicshop/a_mains/msi_unpacker.py
atomicshop/a_mains/process_from_port.py
atomicshop/a_mains/search_for_hyperlinks_in_docx.py
atomicshop/a_mains/set_default_dns_gateway.py
atomicshop/a_mains/update_config_toml.py
atomicshop/a_mains/FACT/factw_fact_extractor_docker_image_main_sudo.py
atomicshop/a_mains/FACT/update_extract.py
atomicshop/a_mains/addons/PlayWrightCodegen.cmd
atomicshop/a_mains/addons/ScriptExecution.cmd
atomicshop/a_mains/addons/inits/init_to_import_all_modules.py
atomicshop-3.11.7.dist-info/licenses/LICENSE.txt
atomicshop-3.11.7.dist-info/METADATA
atomicshop-3.11.7.dist-info/WHEEL
atomicshop-3.11.7.dist-info/top_level.txt
atomicshop-3.11.7.dist-info/RECORD
