Metadata-Version: 2.4
Name: atomicshop
Version: 3.11.7
Summary: Atomic functions and classes to make developer life easier
Author: Denis Kras
License-Expression: MIT
Project-URL: Homepage, https://github.com/BugSec-Official/atomicshop
Classifier: Intended Audience :: Developers
Classifier: Programming Language :: Python :: 3
Classifier: Topic :: Software Development :: Libraries :: Python Modules
Requires-Python: <3.14,>=3.12
License-File: LICENSE.txt
Requires-Dist: wheel
Requires-Dist: setuptools
Requires-Dist: beautifulsoup4==4.14.3
Requires-Dist: cryptography==46.0.3
Requires-Dist: dkarchiver==1.0.1
Requires-Dist: dkinst
Requires-Dist: dnslib==0.9.26
Requires-Dist: dnspython==2.8.0
Requires-Dist: docker==7.1.0
Requires-Dist: flask_socketio==5.5.1
Requires-Dist: google-api-python-client==2.187.0
Requires-Dist: google-genai==1.53.0
Requires-Dist: icmplib==3.0.4
Requires-Dist: numpy
Requires-Dist: olefile==0.47
Requires-Dist: openpyxl==3.1.5
Requires-Dist: pandas==2.3.3
Requires-Dist: paramiko==4.0.0
Requires-Dist: pefile==2024.8.26
Requires-Dist: playwright==1.56.0
Requires-Dist: psutil==7.1.3
Requires-Dist: pymongo==4.15.5
Requires-Dist: pyopenssl==25.3.0
Requires-Dist: python-docx
Requires-Dist: pywin32==311; platform_system == "Windows"
Requires-Dist: SoundCard
Requires-Dist: soundfile
Requires-Dist: SpeechRecognition
Requires-Dist: tldextract==5.3.0
Requires-Dist: websockets==15.0.1
Dynamic: license-file
